{
    "Parameters": {
        "FlowDescription": "Ingestion flow for cdsview cdhdr",
        "DomainName": "dto",
        "SourceName": "sap",
        "SourceObject": "i-dfs-orglmeasurechangedoc",
        "ServiceName": "s3",
        "LayerName": "ing",
        "BucketName": "dto-sap-prd-ing-raw-i-dfs-orglmeasurechangedoc-cdhdr",
        "Object": "/sap/opu/odata/sap/ZAWS_CHANGEDOCUMENT_SRV/I_DFS_OrglMeasureChangeDoc",
        "ConnectorProfileName": "SAP_HEP",
        "ConnectionType": "SAPOData",
        "DataTransferApi": "",
        "IncrementalField": "CreationDate",
        "ScheduleCron": "cron(0 1 ? * * *)"
    }
}